wetterdienst/__init__.py
wetterdienst/api.py
wetterdienst/boot.py
wetterdienst/core/__init__.py
wetterdienst/core/interpolate.py
wetterdienst/core/summarize.py
wetterdienst/core/util.py
wetterdienst/exceptions.py
wetterdienst/io/__init__.py
wetterdienst/io/export.py
wetterdienst/metadata/__init__.py
wetterdienst/metadata/cache.py
wetterdienst/metadata/extension.py
wetterdienst/metadata/parameter.py
wetterdienst/metadata/period.py
wetterdienst/metadata/resolution.py
wetterdienst/model/__init__.py
wetterdienst/model/metadata.py
wetterdienst/model/request.py
wetterdienst/model/result.py
wetterdienst/model/unit.py
wetterdienst/model/util.py
wetterdienst/model/values.py
wetterdienst/provider/__init__.py
wetterdienst/provider/dwd/__init__.py
wetterdienst/provider/dwd/dmo/__init__.py
wetterdienst/provider/dwd/dmo/api.py
wetterdienst/provider/dwd/dmo/metadata.py
wetterdienst/provider/dwd/metadata.py
wetterdienst/provider/dwd/mosmix/__init__.py
wetterdienst/provider/dwd/mosmix/access.py
wetterdienst/provider/dwd/mosmix/api.py
wetterdienst/provider/dwd/mosmix/metadata.py
wetterdienst/provider/dwd/observation/__init__.py
wetterdienst/provider/dwd/observation/api.py
wetterdienst/provider/dwd/observation/download.py
wetterdienst/provider/dwd/observation/fields.py
wetterdienst/provider/dwd/observation/fileindex.py
wetterdienst/provider/dwd/observation/metadata.py
wetterdienst/provider/dwd/observation/metaindex.py
wetterdienst/provider/dwd/observation/parser.py
wetterdienst/provider/dwd/radar/README.md
wetterdienst/provider/dwd/radar/__init__.py
wetterdienst/provider/dwd/radar/api.py
wetterdienst/provider/dwd/radar/cli.py
wetterdienst/provider/dwd/radar/index.py
wetterdienst/provider/dwd/radar/metadata/__init__.py
wetterdienst/provider/dwd/radar/metadata/parameter.py
wetterdienst/provider/dwd/radar/metadata/period.py
wetterdienst/provider/dwd/radar/metadata/resolution.py
wetterdienst/provider/dwd/radar/sites.py
wetterdienst/provider/dwd/radar/util.py
wetterdienst-0.114.3.dist-info/WHEEL
wetterdienst-0.114.3.dist-info/entry_points.txt
wetterdienst-0.114.3.dist-info/METADATA
wetterdienst-0.114.3.dist-info/RECORD
