Metadata-Version: 2.3
Name: wetterdienst
Version: 0.114.3
Summary: Open weather data for humans
Keywords: deutscher-wetterdienst,dmo,eaufrance-hubeau,environment-and-climate-change-canada,environmental-agency-uk,federal-waterways-and-shipping-administration-germany,forecast,geosphere-austria,ghcn,historical,institute-of-meteorology-and-water-management-poland,mosmix,national-oceanic-and-atmospheric-administration,national-weather-service,near-real-time,observation,open-data,open-source,radar,radolan,recent,time-series,weather-api,weather-data,weather-station
Author: Benjamin Gutzmann, Andreas Motl
Author-email: Benjamin Gutzmann <gutzemann@gmail.com>, Andreas Motl <andreas.motl@panodata.org>
License: # MIT License
Classifier: Development Status :: 4 - Beta
Classifier: Environment :: Console
Classifier: Intended Audience :: Developers
Classifier: Intended Audience :: Education
Classifier: Intended Audience :: Information Technology
Classifier: Intended Audience :: Science/Research
Classifier: Intended Audience :: System Administrators
Classifier: License :: OSI Approved :: MIT License
Classifier: Operating System :: MacOS
Classifier: Operating System :: POSIX
Classifier: Operating System :: Unix
Classifier: Programming Language :: Python
Classifier: Programming Language :: Python :: 3 :: Only
Classifier: Programming Language :: Python :: 3.10
Classifier: Programming Language :: Python :: 3.11
Classifier: Programming Language :: Python :: 3.12
Classifier: Programming Language :: Python :: 3.13
Classifier: Topic :: Communications
Classifier: Topic :: Database
Classifier: Topic :: Internet
Classifier: Topic :: Internet :: WWW/HTTP :: Indexing/Search
Classifier: Topic :: Scientific/Engineering :: Atmospheric Science
Classifier: Topic :: Scientific/Engineering :: GIS
Classifier: Topic :: Scientific/Engineering :: Human Machine Interfaces
Classifier: Topic :: Scientific/Engineering :: Hydrology
Classifier: Topic :: Scientific/Engineering :: Information Analysis
Classifier: Topic :: Scientific/Engineering :: Interface Engine/Protocol Translator
Classifier: Topic :: Scientific/Engineering :: Visualization
Classifier: Topic :: Software Development :: Libraries
Classifier: Topic :: System :: Archiving
Classifier: Topic :: Text Processing
Classifier: Topic :: Utilities
Requires-Dist: backports-datetime-fromisoformat>=2 ; python_full_version < '3.11'
Requires-Dist: click>=8,<9
Requires-Dist: cloup>=3.0.1,<4
Requires-Dist: diskcache>=5.4,<6
Requires-Dist: fsspec[http]>=2023.1
Requires-Dist: lxml>=4.9.1,<7
Requires-Dist: measurement>=3.2,<4
Requires-Dist: platformdirs>=4,<5
Requires-Dist: polars[calamine,pyarrow]>=1.15.0,<2
Requires-Dist: portion>=2.4.2,<3
Requires-Dist: pydantic>=2.7.3,<3
Requires-Dist: pydantic-extra-types>=2.10.1,<3
Requires-Dist: pydantic-settings>=2.7.0,<3
Requires-Dist: python-dateutil>=2,<3
Requires-Dist: rapidfuzz>=3.1,<4
Requires-Dist: stamina>=23,<26
Requires-Dist: tabulate>=0.8,<1
Requires-Dist: tqdm>=4,<5
Requires-Dist: tzdata>=2024.2
Requires-Dist: tzfpy>=0.15.2,<2
Requires-Dist: pdbufr>=0.10.2,<1 ; extra == 'bufr'
Requires-Dist: pybufrkit>=0.2,<1 ; extra == 'bufr'
Requires-Dist: pandas>=2,<3 ; extra == 'cratedb'
Requires-Dist: sqlalchemy-cratedb<1 ; extra == 'cratedb'
Requires-Dist: duckdb>=0.9,<2 ; extra == 'duckdb'
Requires-Dist: pandas>=2,<3 ; extra == 'duckdb'
Requires-Dist: eccodes>=1.5.2,<3 ; extra == 'eccodes'
Requires-Dist: xlsxwriter>=3.0.9,<4 ; extra == 'excel'
Requires-Dist: duckdb>=0.9,<2 ; extra == 'explorer'
Requires-Dist: plotly>=5.11,<7 ; extra == 'explorer'
Requires-Dist: statsmodels>=0.14.1,<1 ; extra == 'explorer'
Requires-Dist: streamlit>=1.27,<2 ; extra == 'explorer'
Requires-Dist: pandas>=2,<3 ; extra == 'export'
Requires-Dist: sqlalchemy>=2,<3 ; extra == 'export'
Requires-Dist: xarray>=2023.1,<2026 ; extra == 'export'
Requires-Dist: xlsxwriter>=3.0.9,<4 ; extra == 'export'
Requires-Dist: zarr>=3.1,<4 ; python_full_version >= '3.11' and extra == 'export'
Requires-Dist: influxdb>=5.3,<6 ; extra == 'influxdb'
Requires-Dist: influxdb-client>=1.18,<2 ; extra == 'influxdb'
Requires-Dist: influxdb3-python>=0.3,<1 ; extra == 'influxdb'
Requires-Dist: scipy>=1.14.1,<2 ; extra == 'interpolation'
Requires-Dist: shapely>=2,<3 ; extra == 'interpolation'
Requires-Dist: utm>=0.7,<1 ; extra == 'interpolation'
Requires-Dist: matplotlib>=3.3,<4 ; extra == 'matplotlib'
Requires-Dist: mysqlclient>=2,<3 ; extra == 'mysql'
Requires-Dist: pandas>=2,<3 ; extra == 'mysql'
Requires-Dist: pypdf>=3.12.1,<7 ; extra == 'pdf'
Requires-Dist: kaleido>=0.2.2 ; extra == 'plotting'
Requires-Dist: plotly>=5.24.1 ; extra == 'plotting'
Requires-Dist: psycopg2-binary>=2,<3 ; extra == 'postgresql'
Requires-Dist: h5py>=3.1,<4 ; extra == 'radar'
Requires-Dist: pybufrkit>=0.2,<1 ; extra == 'radarplus'
Requires-Dist: wradlib>=2.0.1,<3 ; extra == 'radarplus'
Requires-Dist: xradar>=0.2,<1 ; extra == 'radarplus'
Requires-Dist: fastapi>=0.95.1,<1 ; extra == 'restapi'
Requires-Dist: httpx>=0.24,<1 ; extra == 'restapi'
Requires-Dist: uvicorn[standard]>=0.14,<1 ; extra == 'restapi'
Requires-Dist: duckdb>=0.9,<2 ; extra == 'sql'
Requires-Python: >=3.10
Project-URL: Explorer, https://wetterdienst.streamlit.app/
Project-URL: Homepage, https://wetterdienst.readthedocs.io/
Project-URL: Issues, https://github.com/earthobservations/wetterdienst/issues
Project-URL: Releases, https://github.com/earthobservations/wetterdienst/releases
Project-URL: Repository, https://github.com/earthobservations/wetterdienst
Project-URL: Restapi, https://wetterdienst.eobs.org/
Project-URL: Stripes, https://stripes.streamlit.app/
Provides-Extra: bufr
Provides-Extra: cratedb
Provides-Extra: duckdb
Provides-Extra: eccodes
Provides-Extra: excel
Provides-Extra: explorer
Provides-Extra: export
Provides-Extra: influxdb
Provides-Extra: interpolation
Provides-Extra: matplotlib
Provides-Extra: mysql
Provides-Extra: pdf
Provides-Extra: plotting
Provides-Extra: postgresql
Provides-Extra: radar
Provides-Extra: radarplus
Provides-Extra: restapi
Provides-Extra: sql
